__init__.py
soundcloud_dl.py
downloader/__init__.py
downloader/client.py
downloader/context.py
downloader/downloader.py
downloader/utils.py
soundcloud_dl-0.1.26.dist-info/METADATA
soundcloud_dl-0.1.26.dist-info/WHEEL
soundcloud_dl-0.1.26.dist-info/entry_points.txt
soundcloud_dl-0.1.26.dist-info/top_level.txt
soundcloud_dl-0.1.26.dist-info/RECORD
