Metadata-Version: 2.1
Name: soundcloud_dl
Version: 0.1.26
Summary: A tool to download tracks from soundcloud.com
Home-page: https://github.com/Suyash458/soundcloud-dl
Author: Suyash Behera
Author-email: sne9x@outlook.com
License: UNKNOWN
Download-URL: https://github.com/Suyash458/soundcloud-dl/archive/master.zip
Keywords: Downloader,Python,soundcloud
Platform: UNKNOWN
Classifier: Development Status :: 5 - Production/Stable
